pymust/__init__.py
pymust/bmode.py
pymust/dasmtx.py
pymust/dasmtx3.py
pymust/genscat.py
pymust/getparam.py
pymust/getpulse.py
pymust/impolgrid.py
pymust/iq2doppler.py
pymust/mkmovie.py
pymust/pfield.py
pymust/pfield3.py
pymust/rf2iq.py
pymust/simus.py
pymust/simus3.py
pymust/smoothn.py
pymust/sptrack.py
pymust/sptrack_old.py
pymust/tgc.py
pymust/txdelay.py
pymust/txdelay3.py
pymust/utils.py
pymust/wfilt.py
pymust/Data/colorMap.pkl
pymust-0.1.9.dist-info/licenses/LICENSE
pymust-0.1.9.dist-info/METADATA
pymust-0.1.9.dist-info/WHEEL
pymust-0.1.9.dist-info/top_level.txt
pymust-0.1.9.dist-info/RECORD
