Metadata-Version: 2.4
Name: PyMUST
Version: 0.1.9
Summary: Python port of the MUST toolbox for ultrasound signal processing and generation of simulated images
Home-page: https://www.biomecardio.com/en//
Author: Gabriel Bernardino (Python port), Damien Garcia (original matlab code)
Author-email: Damien Garcia <damien.garcia@creatis.insa-lyon.fr>, Gabriel Bernardino <gabriel.bernardino@upf.edu>
License: GNU Lesser General Public License v3.0 (LGPL v3)
Project-URL: Homepage, https://www.biomecardio.com/MUST
Project-URL: Repository, https://github.com/creatis-ULTIM/PyMUST
Project-URL: Issues, https://github.com/creatis-ULTIM/PyMUST/issues
Classifier: Programming Language :: Python :: 3
Classifier: Operating System :: OS Independent
Requires-Python: >=3.8
License-File: LICENSE
Requires-Dist: matplotlib
Requires-Dist: numpy
Requires-Dist: scipy
Dynamic: author
Dynamic: home-page
Dynamic: license
Dynamic: license-file
